liquer_pcv/__init__.py
liquer_pcv/commands.py
liquer_pcv/assets/README.md
liquer_pcv/assets/gl.js
liquer_pcv/assets/pointcloud-viewer.wasm
liquer_pcv/assets/quad-url.js
liquer_pcv/assets/sapp_jsutils.js
liquer_pcv-0.4.0.dist-info/METADATA
liquer_pcv-0.4.0.dist-info/WHEEL
liquer_pcv-0.4.0.dist-info/top_level.txt
liquer_pcv-0.4.0.dist-info/RECORD
