Metadata-Version: 2.1
Name: liquer-pcv
Version: 0.4.0
Summary: LiQuer - Pointcloud Viewer is tool for exploratory data analysis.
Home-page: https://github.com/orest-d/pointcloud-viewer-rs
Author: Orest Dubay
Author-email: orest3.dubay@gmail.com
License: UNKNOWN
Platform: UNKNOWN
Classifier: Programming Language :: Python :: 3
Classifier: License :: OSI Approved :: MIT License
Classifier: Operating System :: OS Independent
Requires-Dist: Flask
Requires-Dist: liquer-framework
